{
    "Controller202514078": {
        "phases": [
            "0",
            "1",
            "2",
            "3",
            "4",
            "5",
            "6",
            "7"
        ],
        "minInterval": 50,
        "maxInterval": 50,
        "threshold": 3,
        "sensors": [
            "S13",
            "S14",
            "S12",
            "S15"
        ],
        "PhaseDescriptor": {
            "1": {
                "threshold": 12,
                "maxInterval": 50,
                "minInterval": 50,
                "flows": "1010"
            },
            "0": {
                "threshold": 13,
                "maxInterval": 600,
                "minInterval": 200,
                "flows": "1010"
            },
            "3": {
                "threshold": 12,
                "maxInterval": 50,
                "minInterval": 50,
                "flows": "0000"
            },
            "2": {
                "threshold": 0,
                "maxInterval": 600,
                "minInterval": 200,
                "flows": "1010"
            },
            "5": {
                "threshold": 12,
                "maxInterval": 50,
                "minInterval": 50,
                "flows": "0101"
            },
            "4": {
                "threshold": 26,
                "maxInterval": 600,
                "minInterval": 200,
                "flows": "0101"
            },
            "7": {
                "threshold": 12,
                "maxInterval": 50,
                "minInterval": 50,
                "flows": "0000"
            },
            "6": {
                "threshold": 8,
                "maxInterval": 600,
                "minInterval": 200,
                "flows": "0101"
            }
        }
    },
    "Controller1443088096": {
        "phases": [
            "0",
            "1",
            "2",
            "3",
            "4",
            "5",
            "6",
            "7"
        ],
        "minInterval": 50,
        "maxInterval": 50,
        "threshold": 3,
        "sensors": [
            "S32",
            "S33",
            "S34",
            "S35"
        ],
        "PhaseDescriptor": {
            "1": {
                "threshold": 12,
                "maxInterval": 50,
                "minInterval": 50,
                "flows": "1100"
            },
            "0": {
                "threshold": 1,
                "maxInterval": 600,
                "minInterval": 200,
                "flows": "1100"
            },
            "3": {
                "threshold": 12,
                "maxInterval": 50,
                "minInterval": 50,
                "flows": "0000"
            },
            "2": {
                "threshold": 0,
                "maxInterval": 600,
                "minInterval": 200,
                "flows": "1100"
            },
            "5": {
                "threshold": 12,
                "maxInterval": 50,
                "minInterval": 50,
                "flows": "0001"
            },
            "4": {
                "threshold": 0,
                "maxInterval": 600,
                "minInterval": 200,
                "flows": "1011"
            },
            "7": {
                "threshold": 12,
                "maxInterval": 50,
                "minInterval": 50,
                "flows": "0000"
            },
            "6": {
                "threshold": 0,
                "maxInterval": 600,
                "minInterval": 200,
                "flows": "0001"
            }
        }
    },
    "Controller202407913": {
        "phases": [
            "0",
            "1",
            "2",
            "3",
            "4",
            "5"
        ],
        "minInterval": 50,
        "maxInterval": 50,
        "threshold": 3,
        "sensors": [
            "S11",
            "S10",
            "S9"
        ],
        "PhaseDescriptor": {
            "1": {
                "threshold": 12,
                "maxInterval": 50,
                "minInterval": 50,
                "flows": "011"
            },
            "0": {
                "threshold": 5,
                "maxInterval": 600,
                "minInterval": 200,
                "flows": "011"
            },
            "3": {
                "threshold": 12,
                "maxInterval": 50,
                "minInterval": 50,
                "flows": "000"
            },
            "2": {
                "threshold": 0,
                "maxInterval": 600,
                "minInterval": 200,
                "flows": "011"
            },
            "5": {
                "threshold": 12,
                "maxInterval": 50,
                "minInterval": 50,
                "flows": "000"
            },
            "4": {
                "threshold": 17,
                "maxInterval": 600,
                "minInterval": 200,
                "flows": "100"
            }
        }
    },
    "Controller1443088101": {
        "phases": [
            "0",
            "1",
            "2",
            "3",
            "4",
            "5",
            "6",
            "7"
        ],
        "minInterval": 50,
        "maxInterval": 50,
        "threshold": 3,
        "sensors": [
            "S1",
            "S2",
            "S4",
            "S3"
        ],
        "PhaseDescriptor": {
            "1": {
                "threshold": 12,
                "maxInterval": 50,
                "minInterval": 50,
                "flows": "1100"
            },
            "0": {
                "threshold": 26,
                "maxInterval": 600,
                "minInterval": 200,
                "flows": "1100"
            },
            "3": {
                "threshold": 12,
                "maxInterval": 50,
                "minInterval": 50,
                "flows": "0000"
            },
            "2": {
                "threshold": 1,
                "maxInterval": 600,
                "minInterval": 200,
                "flows": "1100"
            },
            "5": {
                "threshold": 12,
                "maxInterval": 50,
                "minInterval": 50,
                "flows": "0011"
            },
            "4": {
                "threshold": 20,
                "maxInterval": 600,
                "minInterval": 200,
                "flows": "0011"
            },
            "7": {
                "threshold": 12,
                "maxInterval": 50,
                "minInterval": 50,
                "flows": "0000"
            },
            "6": {
                "threshold": 0,
                "maxInterval": 600,
                "minInterval": 200,
                "flows": "0011"
            }
        }
    },
    "Controller3010263944": {
        "phases": [
            "0",
            "1",
            "2",
            "3",
            "4",
            "5",
            "6",
            "7"
        ],
        "minInterval": 50,
        "maxInterval": 50,
        "threshold": 3,
        "sensors": [
            "S24",
            "S25",
            "S27",
            "S26"
        ],
        "PhaseDescriptor": {
            "1": {
                "threshold": 12,
                "maxInterval": 50,
                "minInterval": 50,
                "flows": "1100"
            },
            "0": {
                "threshold": 3,
                "maxInterval": 600,
                "minInterval": 200,
                "flows": "1100"
            },
            "3": {
                "threshold": 12,
                "maxInterval": 50,
                "minInterval": 50,
                "flows": "0000"
            },
            "2": {
                "threshold": 7,
                "maxInterval": 600,
                "minInterval": 200,
                "flows": "1100"
            },
            "5": {
                "threshold": 12,
                "maxInterval": 50,
                "minInterval": 50,
                "flows": "0011"
            },
            "4": {
                "threshold": 19,
                "maxInterval": 600,
                "minInterval": 200,
                "flows": "0011"
            },
            "7": {
                "threshold": 12,
                "maxInterval": 50,
                "minInterval": 50,
                "flows": "0000"
            },
            "6": {
                "threshold": 0,
                "maxInterval": 600,
                "minInterval": 200,
                "flows": "0011"
            }
        }
    }
}